odoo/addons/energy_selfconsumption/__init__.py
odoo/addons/energy_selfconsumption/__manifest__.py
odoo/addons/energy_selfconsumption/controllers/__init__.py
odoo/addons/energy_selfconsumption/controllers/controllers.py
odoo/addons/energy_selfconsumption/controllers/inscriptions_form_controllers.py
odoo/addons/energy_selfconsumption/data/contract_line_qty_formula_data.xml
odoo/addons/energy_selfconsumption/data/custom_paper_format_views.xml
odoo/addons/energy_selfconsumption/data/ir_attachment_data.xml
odoo/addons/energy_selfconsumption/data/ir_cron.xml
odoo/addons/energy_selfconsumption/data/ir_sequence_data.xml
odoo/addons/energy_selfconsumption/data/mail_template.xml
odoo/addons/energy_selfconsumption/data/project_type_data.xml
odoo/addons/energy_selfconsumption/data/service_available_data.xml
odoo/addons/energy_selfconsumption/demo/energy_selfconsumption_demo.xml
odoo/addons/energy_selfconsumption/i18n/ca_ES.po
odoo/addons/energy_selfconsumption/i18n/energy_selfconsumption.pot
odoo/addons/energy_selfconsumption/i18n/es.po
odoo/addons/energy_selfconsumption/i18n/eu_ES.po
odoo/addons/energy_selfconsumption/migrations/14.0.3.4.0/post-migration.py
odoo/addons/energy_selfconsumption/models/__init__.py
odoo/addons/energy_selfconsumption/models/account_move.py
odoo/addons/energy_selfconsumption/models/contract.py
odoo/addons/energy_selfconsumption/models/contract_csv_report.py
odoo/addons/energy_selfconsumption/models/contract_line.py
odoo/addons/energy_selfconsumption/models/create_distribution_table.py
odoo/addons/energy_selfconsumption/models/create_inscription.py
odoo/addons/energy_selfconsumption/models/distribution_table.py
odoo/addons/energy_selfconsumption/models/distribution_table_csv_report.py
odoo/addons/energy_selfconsumption/models/inscription.py
odoo/addons/energy_selfconsumption/models/participation.py
odoo/addons/energy_selfconsumption/models/partner.py
odoo/addons/energy_selfconsumption/models/product.py
odoo14_addon_energy_selfconsumption-14.0.5.2.6.dist-info/METADATA
odoo14_addon_energy_selfconsumption-14.0.5.2.6.dist-info/WHEEL
odoo14_addon_energy_selfconsumption-14.0.5.2.6.dist-info/top_level.txt
odoo14_addon_energy_selfconsumption-14.0.5.2.6.dist-info/RECORD
