Metadata-Version: 2.1
Name: odoo14-addon-energy-selfconsumption
Version: 14.0.5.2.6
Summary: Module for energetic self-consumption projects.
Home-page: https://coopdevs.org
Author: Coopdevs Treball SCCL & Som Energia SCCL
Classifier: Programming Language :: Python
Classifier: Framework :: Odoo
Classifier: Framework :: Odoo :: 14.0
Requires-Python: >=3.6
Requires-Dist: numpy >=1.24.4
Requires-Dist: odoo14-addon-contract-mandate ==14.0.1.0.1
Requires-Dist: odoo14-addon-contract-queue-job ==14.0.1.0.1.dev3
Requires-Dist: odoo14-addon-contract-variable-quantity ==14.0.1.0.1.dev5
Requires-Dist: odoo14-addon-contract ==14.0.2.9.4.dev2
Requires-Dist: odoo14-addon-energy-communities-cooperator >=14.0.1.0.2
Requires-Dist: odoo14-addon-energy-communities >=14.0.9.4.0
Requires-Dist: odoo14-addon-energy-project ==14.0.3.5.0
Requires-Dist: odoo14-addon-report-csv ==14.0.1.0.1.dev5
Requires-Dist: odoo14-addon-web-m2x-options ==14.0.1.1.1
Requires-Dist: odoo <14.1dev,>=14.0a
Requires-Dist: openupgradelib >=3.6.1
Requires-Dist: pandas >=2.0.3
